{
    "id": 137582,
    "song_id": 39593,
    "song_name": "Boulevard Of Broken Dreams",
    "artist_id": 1368,
    "artist_name": "Green Day",
    "type": "Bass Tabs",
    "part": "",
    "version": 1,
    "votes": 241,
    "difficulty": "",
    "rating": 4.58366,
    "date": "1095552000",
    "status": "approved",
    "preset_id": 761,
    "tab_access_type": "public",
    "tp_version": 0,
    "tonality_name": "",
    "version_description": null,
    "verified": 0,
    "recording": {
        "is_acoustic": 0,
        "tonality_name": "",
        "performance": null,
        "recording_artists": [],
        "video_urls": null,
        "album_id": 247
    },
    "album_cover": {
        "has_album_cover": true,
        "app_album_cover": {
            "small": "https://www.ultimate-guitar.com/static/s3/ugdb-p1/media/album/cover/1/1/119002/primary-cover.jpg@200?c=1"
        }
    },
    "artist_cover": {
        "has_artist_cover": true,
        "app_artist_cover": {
            "small": "https://www.ultimate-guitar.com/static/s3/ugdb-p1/media/artist/cover/3/5/35/primary-cover.jpg@200?c=1"
        }
    },
    "unique_chords": "",
    "ug_difficulty": "",
    "date_update": 1463145836,
    "source": "",
    "versions": [
        {
            "id": 149719,
            "song_id": 39593,
            "song_name": "Boulevard Of Broken Dreams",
            "artist_id": 1368,
            "artist_name": "Green Day",
            "type": "Bass Tabs",
            "part": "",
            "version": 2,
            "votes": 14,
            "difficulty": "",
            "rating": 4.31787,
            "date": "1102291200",
            "status": "approved",
            "preset_id": 761,
            "tab_access_type": "public",
            "tp_version": 0,
            "tonality_name": "",
            "version_description": null,
            "verified": 0,
            "recording": {
                "is_acoustic": 0,
                "tonality_name": "",
                "performance": null,
                "recording_artists": [],
                "video_urls": null,
                "album_id": 247
            },
            "album_cover": {
                "has_album_cover": true,
                "app_album_cover": {
                    "small": "https://www.ultimate-guitar.com/static/s3/ugdb-p1/media/album/cover/1/1/119002/primary-cover.jpg@200?c=1"
                }
            },
            "artist_cover": {
                "has_artist_cover": true,
                "app_artist_cover": {
                    "small": "https://www.ultimate-guitar.com/static/s3/ugdb-p1/media/artist/cover/3/5/35/primary-cover.jpg@200?c=1"
                }
            },
            "unique_chords": "",
            "ug_difficulty": "",
            "date_update": 1102291200,
            "source": ""
        },
        {
            "id": 157122,
            "song_id": 39593,
            "song_name": "Boulevard Of Broken Dreams",
            "artist_id": 1368,
            "artist_name": "Green Day",
            "type": "Bass Tabs",
            "part": "",
            "version": 3,
            "votes": 14,
            "difficulty": "",
            "rating": 3.96491,
            "date": "1105488000",
            "status": "approved",
            "preset_id": 761,
            "tab_access_type": "public",
            "tp_version": 0,
            "tonality_name": "",
            "version_description": null,
            "verified": 0,
            "recording": {
                "is_acoustic": 0,
                "tonality_name": "",
                "performance": null,
                "recording_artists": [],
                "video_urls": null,
                "album_id": 247
            },
            "album_cover": {
                "has_album_cover": true,
                "app_album_cover": {
                    "small": "https://www.ultimate-guitar.com/static/s3/ugdb-p1/media/album/cover/1/1/119002/primary-cover.jpg@200?c=1"
                }
            },
            "artist_cover": {
                "has_artist_cover": true,
                "app_artist_cover": {
                    "small": "https://www.ultimate-guitar.com/static/s3/ugdb-p1/media/artist/cover/3/5/35/primary-cover.jpg@200?c=1"
                }
            },
            "unique_chords": "",
            "ug_difficulty": "",
            "date_update": 1105488000,
            "source": ""
        },
        {
            "id": 178830,
            "song_id": 39593,
            "song_name": "Boulevard Of Broken Dreams",
            "artist_id": 1368,
            "artist_name": "Green Day",
            "type": "Bass Tabs",
            "part": "",
            "version": 4,
            "votes": 16,
            "difficulty": "",
            "rating": 3.60021,
            "date": "1113782400",
            "status": "approved",
            "preset_id": 761,
            "tab_access_type": "public",
            "tp_version": 0,
            "tonality_name": "",
            "version_description": "",
            "verified": 0,
            "recording": {
                "is_acoustic": 0,
                "tonality_name": "",
                "performance": null,
                "recording_artists": [],
                "video_urls": null,
                "album_id": 247
            },
            "album_cover": {
                "has_album_cover": true,
                "app_album_cover": {
                    "small": "https://www.ultimate-guitar.com/static/s3/ugdb-p1/media/album/cover/1/1/119002/primary-cover.jpg@200?c=1"
                }
            },
            "artist_cover": {
                "has_artist_cover": true,
                "app_artist_cover": {
                    "small": "https://www.ultimate-guitar.com/static/s3/ugdb-p1/media/artist/cover/3/5/35/primary-cover.jpg@200?c=1"
                }
            },
            "unique_chords": "",
            "ug_difficulty": "",
            "date_update": 1585354412,
            "source": ""
        },
        {
            "id": 870903,
            "song_id": 39593,
            "song_name": "Boulevard Of Broken Dreams",
            "artist_id": 1368,
            "artist_name": "Green Day",
            "type": "Bass Tabs",
            "part": "",
            "version": 5,
            "votes": 3,
            "difficulty": "novice",
            "rating": 3.734,
            "date": "1252368001",
            "status": "approved",
            "preset_id": 761,
            "tab_access_type": "public",
            "tp_version": 0,
            "tonality_name": "",
            "version_description": null,
            "verified": 0,
            "recording": {
                "is_acoustic": 0,
                "tonality_name": "",
                "performance": null,
                "recording_artists": [],
                "video_urls": null,
                "album_id": 247
            },
            "album_cover": {
                "has_album_cover": true,
                "app_album_cover": {
                    "small": "https://www.ultimate-guitar.com/static/s3/ugdb-p1/media/album/cover/1/1/119002/primary-cover.jpg@200?c=1"
                }
            },
            "artist_cover": {
                "has_artist_cover": true,
                "app_artist_cover": {
                    "small": "https://www.ultimate-guitar.com/static/s3/ugdb-p1/media/artist/cover/3/5/35/primary-cover.jpg@200?c=1"
                }
            },
            "unique_chords": "",
            "ug_difficulty": "",
            "date_update": 1252368001,
            "source": ""
        },
        {
            "id": 2406781,
            "song_id": 39593,
            "song_name": "Boulevard Of Broken Dreams",
            "artist_id": 1368,
            "artist_name": "Green Day",
            "type": "Bass Tabs",
            "part": "",
            "version": 6,
            "votes": 0,
            "difficulty": "intermediate",
            "rating": 0,
            "date": "1529495200",
            "status": "approved",
            "preset_id": 761,
            "tab_access_type": "public",
            "tp_version": 0,
            "tonality_name": "",
            "version_description": "Any of the parts that are repeated a lot I noted using \"(repeated [number of times repeated]x)\". Also instead of using the 5th fret on the Ab string during the ending, I chose to just use an open Db note.",
            "verified": 0,
            "recording": {
                "is_acoustic": 0,
                "tonality_name": "",
                "performance": null,
                "recording_artists": [],
                "video_urls": null,
                "album_id": 247
            },
            "album_cover": {
                "has_album_cover": true,
                "app_album_cover": {
                    "small": "https://www.ultimate-guitar.com/static/s3/ugdb-p1/media/album/cover/1/1/119002/primary-cover.jpg@200?c=1"
                }
            },
            "artist_cover": {
                "has_artist_cover": true,
                "app_artist_cover": {
                    "small": "https://www.ultimate-guitar.com/static/s3/ugdb-p1/media/artist/cover/3/5/35/primary-cover.jpg@200?c=1"
                }
            },
            "unique_chords": "",
            "ug_difficulty": "",
            "date_update": 1529495200,
            "source": ""
        }
    ],
    "userRating": 0,
    "tuning": "E A D G",
    "capo": 0,
    "urlWeb": "https://tabs.ultimate-guitar.com/tab/green-day/boulevard-of-broken-dreams-bass-137582",
    "strumming": [],
    "videosCount": 1105,
    "comments_count": 28,
    "contributor": {
        "user_id": 51904,
        "username": "greendaze"
    },
    "advertising": {
        "targeting_song_genre": "rock"
    },
    "versions_count": 58,
    "pro_brother": {
        "id": 1910951,
        "song_id": 39593,
        "song_name": "Boulevard Of Broken Dreams",
        "artist_id": 1368,
        "artist_name": "Green Day",
        "type": "Official",
        "part": "",
        "version": 1,
        "votes": 3938,
        "difficulty": "",
        "rating": 4.80904,
        "date": "1481896217",
        "status": "approved",
        "preset_id": 761,
        "tab_access_type": "public",
        "tp_version": 0,
        "tonality_name": "Fm",
        "version_description": "",
        "verified": 0,
        "recording": {
            "is_acoustic": 0,
            "tonality_name": "",
            "performance": null,
            "recording_artists": [],
            "video_urls": null,
            "album_id": 247
        },
        "album_cover": {
            "has_album_cover": true,
            "app_album_cover": {
                "small": "https://www.ultimate-guitar.com/static/s3/ugdb-p1/media/album/cover/1/1/119002/primary-cover.jpg@200?c=1"
            }
        },
        "artist_cover": {
            "has_artist_cover": true,
            "app_artist_cover": {
                "small": "https://www.ultimate-guitar.com/static/s3/ugdb-p1/media/artist/cover/3/5/35/primary-cover.jpg@200?c=1"
            }
        },
        "unique_chords": "",
        "ug_difficulty": "",
        "date_update": 1753714623,
        "source": ""
    },
    "recommended": [
        {
            "id": 6125,
            "song_id": 19556,
            "song_name": "Wonderwall",
            "artist_id": 734,
            "artist_name": "Oasis",
            "type": "Chords",
            "part": "",
            "version": 1,
            "votes": 2448,
            "difficulty": "intermediate",
            "rating": 4.59015,
            "date": "1004486400",
            "status": "approved",
            "preset_id": 2332,
            "tab_access_type": "public",
            "tp_version": 0,
            "tonality_name": "F#m",
            "version_description": "",
            "verified": 0,
            "recording": {
                "is_acoustic": 0,
                "tonality_name": "",
                "performance": null,
                "recording_artists": [],
                "video_urls": null,
                "album_id": 148
            },
            "album_cover": {
                "has_album_cover": true,
                "app_album_cover": {
                    "small": "https://www.ultimate-guitar.com/static/s3/ugdb-p1/media/album/cover/2/9/297362/primary-cover.jpg@200?c=1"
                }
            },
            "artist_cover": {
                "has_artist_cover": true,
                "app_artist_cover": {
                    "small": "https://www.ultimate-guitar.com/static/s3/ugdb-p1/media/artist/cover/1/8/182456/primary-cover.jpg@200?c=1"
                }
            },
            "unique_chords": "",
            "ug_difficulty": "",
            "date_update": 1589132708,
            "source": ""
        },
        {
            "id": 137011,
            "song_id": 39790,
            "song_name": "Wake Me Up When September Ends",
            "artist_id": 1368,
            "artist_name": "Green Day",
            "type": "Tabs",
            "part": "",
            "version": 1,
            "votes": 163,
            "difficulty": "",
            "rating": 4.29764,
            "date": "1095120000",
            "status": "approved",
            "preset_id": 2219,
            "tab_access_type": "public",
            "tp_version": 0,
            "tonality_name": "G",
            "version_description": "",
            "verified": 0,
            "recording": {
                "is_acoustic": 0,
                "tonality_name": "",
                "performance": null,
                "recording_artists": [],
                "video_urls": null,
                "album_id": 247
            },
            "album_cover": {
                "has_album_cover": true,
                "app_album_cover": {
                    "small": "https://www.ultimate-guitar.com/static/s3/ugdb-p1/media/album/cover/2/0/2081766/primary-cover.jpg@200?c=1"
                }
            },
            "artist_cover": {
                "has_artist_cover": true,
                "app_artist_cover": {
                    "small": "https://www.ultimate-guitar.com/static/s3/ugdb-p1/media/artist/cover/3/5/35/primary-cover.jpg@200?c=1"
                }
            },
            "unique_chords": "",
            "ug_difficulty": "",
            "date_update": 1484818026,
            "source": ""
        },
        {
            "id": 1956589,
            "song_id": 1710759,
            "song_name": "Perfect",
            "artist_id": 30232,
            "artist_name": "Ed Sheeran",
            "type": "Chords",
            "part": "",
            "version": 1,
            "votes": 53561,
            "difficulty": "novice",
            "rating": 4.86008,
            "date": "1488453515",
            "status": "approved",
            "preset_id": 18913,
            "tab_access_type": "public",
            "tp_version": 0,
            "tonality_name": "Ab",
            "version_description": "",
            "verified": 0,
            "recording": {
                "is_acoustic": 0,
                "tonality_name": "",
                "performance": null,
                "recording_artists": [],
                "video_urls": null,
                "album_id": 11229
            },
            "album_cover": {
                "has_album_cover": true,
                "app_album_cover": {
                    "small": "https://www.ultimate-guitar.com/static/s3/ugdb-p1/media/album/cover/1/5/1564216/primary-cover.jpg@200?c=1"
                }
            },
            "artist_cover": {
                "has_artist_cover": true,
                "app_artist_cover": {
                    "small": "https://www.ultimate-guitar.com/static/s3/ugdb-p1/media/artist/cover/5/2/5219/primary-cover.jpg@200?c=1"
                }
            },
            "unique_chords": "",
            "ug_difficulty": "",
            "date_update": 1679839047,
            "source": ""
        },
        {
            "id": 1171909,
            "song_id": 313255,
            "song_name": "Radioactive",
            "artist_id": 36784,
            "artist_name": "Imagine Dragons",
            "type": "Chords",
            "part": "",
            "version": 1,
            "votes": 21286,
            "difficulty": "novice",
            "rating": 4.87914,
            "date": "1343779201",
            "status": "approved",
            "preset_id": 2616,
            "tab_access_type": "public",
            "tp_version": 0,
            "tonality_name": "Bm",
            "version_description": "",
            "verified": 0,
            "recording": {
                "is_acoustic": 0,
                "tonality_name": "",
                "performance": null,
                "recording_artists": [],
                "video_urls": null,
                "album_id": 8596
            },
            "album_cover": {
                "has_album_cover": true,
                "app_album_cover": {
                    "small": "https://www.ultimate-guitar.com/static/s3/ugdb-p1/media/album/cover/2/7/2774185/primary-cover.jpg@200?c=1"
                }
            },
            "artist_cover": {
                "has_artist_cover": true,
                "app_artist_cover": {
                    "small": "https://www.ultimate-guitar.com/static/s3/ugdb-p1/media/artist/cover/1/5/1527/primary-cover.jpg@200?c=1"
                }
            },
            "unique_chords": "",
            "ug_difficulty": "",
            "date_update": 1558571800,
            "source": ""
        },
        {
            "id": 821963,
            "song_id": 39550,
            "song_name": "21 Guns",
            "artist_id": 1368,
            "artist_name": "Green Day",
            "type": "Tabs",
            "part": "",
            "version": 2,
            "votes": 71,
            "difficulty": "",
            "rating": 4.55953,
            "date": "1241740801",
            "status": "approved",
            "preset_id": 2293,
            "tab_access_type": "public",
            "tp_version": 0,
            "tonality_name": "",
            "version_description": "",
            "verified": 0,
            "recording": {
                "is_acoustic": 0,
                "tonality_name": "",
                "performance": null,
                "recording_artists": [],
                "video_urls": null,
                "album_id": 249
            },
            "album_cover": {
                "has_album_cover": true,
                "app_album_cover": {
                    "small": "https://www.ultimate-guitar.com/static/s3/ugdb-p1/media/album/cover/2/9/299487/primary-cover.jpg@200?c=1"
                }
            },
            "artist_cover": {
                "has_artist_cover": true,
                "app_artist_cover": {
                    "small": "https://www.ultimate-guitar.com/static/s3/ugdb-p1/media/artist/cover/3/5/35/primary-cover.jpg@200?c=1"
                }
            },
            "unique_chords": "",
            "ug_difficulty": "",
            "date_update": 1484906500,
            "source": ""
        },
        {
            "id": 1137467,
            "song_id": 298037,
            "song_name": "Let Her Go",
            "artist_id": 21762,
            "artist_name": "Passenger",
            "type": "Chords",
            "part": "",
            "version": 1,
            "votes": 25416,
            "difficulty": "novice",
            "rating": 4.85605,
            "date": "1331596801",
            "status": "approved",
            "preset_id": 2333,
            "tab_access_type": "public",
            "tp_version": 0,
            "tonality_name": "Em",
            "version_description": "",
            "verified": 0,
            "recording": {
                "is_acoustic": 0,
                "tonality_name": "",
                "performance": null,
                "recording_artists": [],
                "video_urls": [
                    "https://www.youtube.com/watch?v=RBumgq5yVrA"
                ],
                "album_id": 27071
            },
            "album_cover": {
                "has_album_cover": true,
                "app_album_cover": {
                    "small": "https://www.ultimate-guitar.com/static/s3/ugdb-p1/media/album/cover/4/2/423535/primary-cover.jpg@200?c=1"
                }
            },
            "artist_cover": {
                "has_artist_cover": true,
                "app_artist_cover": {
                    "small": "https://www.ultimate-guitar.com/static/s3/ugdb-p1/media/artist/cover/2/8/2861/primary-cover.jpg@200?c=1"
                }
            },
            "unique_chords": "",
            "ug_difficulty": "",
            "date_update": 1612388289,
            "source": ""
        },
        {
            "id": 27336,
            "song_id": 135952,
            "song_name": "Hallelujah",
            "artist_id": 9898,
            "artist_name": "Jeff Buckley",
            "type": "Chords",
            "part": "",
            "version": 1,
            "votes": 5958,
            "difficulty": "novice",
            "rating": 4.84861,
            "date": "1018396800",
            "status": "approved",
            "preset_id": 125,
            "tab_access_type": "public",
            "tp_version": 0,
            "tonality_name": "Db",
            "version_description": "",
            "verified": 0,
            "recording": {
                "is_acoustic": 0,
                "tonality_name": "",
                "performance": null,
                "recording_artists": [],
                "video_urls": null,
                "album_id": 3357
            },
            "album_cover": {
                "has_album_cover": true,
                "app_album_cover": {
                    "small": "https://www.ultimate-guitar.com/static/s3/ugdb-p1/media/album/cover/1/1/115842/primary-cover.jpg@200?c=1"
                }
            },
            "artist_cover": {
                "has_artist_cover": true,
                "app_artist_cover": {
                    "small": "https://www.ultimate-guitar.com/static/s3/ugdb-p1/media/artist/cover/2/4/245/primary-cover.jpg@200?c=1"
                }
            },
            "unique_chords": "",
            "ug_difficulty": "",
            "date_update": 1739839608,
            "source": ""
        }
    ],
    "content": "------------------------------------------------------------------\r\nGREEN DAY - BOULEVARD OF BROKEN DREAMS (AMERICAN IDIOT) \r\n------------------------------------------------------------------\r\n\r\n[ Tabber: LUIZ MANZANO (BRASIL) ]\r\n[ e-mail: lukdeluca@yahoo.com.br ]\r\n\r\n\r\n[Verse]\r\n\r\n[tab]\"Don't know where it goes....\" (5x)\r\nG|------------------------|\r\nD|------------------------|\r\nA|-----------6-6\\1-11-----|\r\nE|1-1/4-44--4-------4\\1---|[/tab]\r\n\r\n[tab]\"I walk....\"\r\n(before chorus)\r\nG|----------------------|\r\nD|----------------------|\r\nA|---------66\\1-11-13---|\r\nE|11/4-44-4-------------|[/tab]\r\n\r\n\r\n[Chorus]\r\n\r\n[tab]\"My shadows are the only one that walks beside me...\"\r\nG|-----------------------------------------------------------------|\r\nD|-----------------------------------------------------------------|\r\nA|4444----6666----4444----6666----4444----6666----4444----333333---|\r\nE|----4444----1111----4444----1111----4444----1111----4444---------|[/tab]\r\n\r\n[tab]\"Ah ah..., I'm walking down the line...\" (9x)\r\nG|------------------------|\r\nD|------------------------|\r\nA|-----------6-6\\1-11-----|\r\nE|1-1/4-44--4-------4\\1---|[/tab]\r\n\r\n[tab]\"I walk....\"\r\n(before chorus)\r\nG|----------------------|\r\nD|----------------------|\r\nA|---------66\\1-11-13---|\r\nE|11/4-44-4-------------|[/tab]\r\n\r\n[tab]\"Ah ah, ah ah...\" \r\nG|--------------------------------------------|\r\nD|--------------------------------------------|\r\nA|-----------6-6\\1-11------------66\\1-11-13---|\r\nE|1-1/4-44--4-------4\\1-11/4-44-4-------------|[/tab]\r\n\r\n\r\n[Solo]\r\n\r\n[tab]G|------------------------------------------------------------------------|\r\nD|------------------------------------------------------------------------|\r\nA|4444----6666----4444----6666----44------6666----44------3333333333333---|\r\nE|----4444----1111----4444----1111----44------1111----44------------------|[/tab]\r\n\r\nonly guitar and vocal...\r\n\r\n[tab]\"... my shadows are the only one that walks beside me...\"\r\nG|-------------------------------------------------------------------------------|\r\nD|-------------------------------------------------------------------------------|\r\nA|11-34444----6666----4444----6666----4444----6666----4444----3333333333333333---|\r\nE|--------4444----1111----4444----1111----4444----1111----4444-------------------|[/tab]\r\n\r\n\r\n[Final riff]\r\n\r\n[tab]G|--------------------------------------------------------------------------------------|\r\nD|--------------------------------------------------------------------------------------|\r\nA|-----4-44-6-66-5-55-------------4-44-6-66-5-55-------------4-44-6-66-5-55-------------|\r\nE|1-11---------------4-44-0-001-11--------------4-44-0-001-11--------------4-44-0-001-11|[/tab]\r\n\r\n[tab]G|-------------------|\r\nD|-------------------|\r\nA|4-44-6-66-5-55-----|\r\nE|---------------4400|[/tab]\r\n\r\n\r\n*********************************\r\n\r\n| /  slide up\r\n| \\  slide down\r\n| h  hammer-on\r\n| p  pull-off\r\n| ~  vibrato\r\n| +  harmonic\r\n| x  Mute note\r\n\r\n*********************************",
    "is_backing_track_under_review": false,
    "is_tab_ml": false
}