{
    "id": 3248528,
    "song_id": 3983627,
    "song_name": "Wishing Well",
    "artist_id": 145437,
    "artist_name": "Juice WRLD",
    "type": "Chords",
    "part": "",
    "version": 2,
    "votes": 136,
    "difficulty": "novice",
    "rating": 4.9166,
    "date": "1594807689",
    "status": "approved",
    "preset_id": 46514,
    "tab_access_type": "public",
    "tp_version": 0,
    "tonality_name": "C",
    "version_description": "This version has an added Dm chord, adding a bit more detail. This isn't perfect, as other chords are present in the song, but it is a simplified version for playing on a guitar. No capo.",
    "verified": 0,
    "recording": {
        "is_acoustic": 0,
        "tonality_name": "",
        "performance": null,
        "recording_artists": [],
        "video_urls": null,
        "album_id": 576839
    },
    "album_cover": {
        "has_album_cover": true,
        "app_album_cover": {
            "small": "https://www.ultimate-guitar.com/static/s3/ugdb-p1/media/album/cover/1/6/1658843/primary-cover.jpg@200?c=1"
        }
    },
    "artist_cover": {
        "has_artist_cover": true,
        "app_artist_cover": {
            "small": "https://www.ultimate-guitar.com/static/s3/ugdb-p1/media/artist/cover/1/8/187365/primary-cover.jpg@200?c=1"
        }
    },
    "unique_chords": "",
    "ug_difficulty": "beginner",
    "date_update": 1594854531,
    "source": "",
    "versions": [
        {
            "id": 3242030,
            "song_id": 3983627,
            "song_name": "Wishing Well",
            "artist_id": 145437,
            "artist_name": "Juice WRLD",
            "type": "Chords",
            "part": "",
            "version": 1,
            "votes": 10,
            "difficulty": "",
            "rating": 4.64646,
            "date": "1594459856",
            "status": "approved",
            "preset_id": 46514,
            "tab_access_type": "public",
            "tp_version": 0,
            "tonality_name": "",
            "version_description": "",
            "verified": 0,
            "recording": {
                "is_acoustic": 0,
                "tonality_name": "",
                "performance": null,
                "recording_artists": [],
                "video_urls": null,
                "album_id": 576839
            },
            "album_cover": {
                "has_album_cover": true,
                "app_album_cover": {
                    "small": "https://www.ultimate-guitar.com/static/s3/ugdb-p1/media/album/cover/1/6/1658843/primary-cover.jpg@200?c=1"
                }
            },
            "artist_cover": {
                "has_artist_cover": true,
                "app_artist_cover": {
                    "small": "https://www.ultimate-guitar.com/static/s3/ugdb-p1/media/artist/cover/1/8/187365/primary-cover.jpg@200?c=1"
                }
            },
            "unique_chords": "",
            "ug_difficulty": "",
            "date_update": 1594459856,
            "source": ""
        },
        {
            "id": 3255296,
            "song_id": 3983627,
            "song_name": "Wishing Well",
            "artist_id": 145437,
            "artist_name": "Juice WRLD",
            "type": "Chords",
            "part": "",
            "version": 3,
            "votes": 0,
            "difficulty": "novice",
            "rating": 0,
            "date": "1595236429",
            "status": "approved",
            "preset_id": 46514,
            "tab_access_type": "public",
            "tp_version": 0,
            "tonality_name": "Am",
            "version_description": "",
            "verified": 0,
            "recording": {
                "is_acoustic": 0,
                "tonality_name": "",
                "performance": null,
                "recording_artists": [],
                "video_urls": null,
                "album_id": 576839
            },
            "album_cover": {
                "has_album_cover": true,
                "app_album_cover": {
                    "small": "https://www.ultimate-guitar.com/static/s3/ugdb-p1/media/album/cover/1/6/1658843/primary-cover.jpg@200?c=1"
                }
            },
            "artist_cover": {
                "has_artist_cover": true,
                "app_artist_cover": {
                    "small": "https://www.ultimate-guitar.com/static/s3/ugdb-p1/media/artist/cover/1/8/187365/primary-cover.jpg@200?c=1"
                }
            },
            "unique_chords": "",
            "ug_difficulty": "",
            "date_update": 1595236429,
            "source": ""
        }
    ],
    "userRating": 0,
    "tuning": "E A D G B E",
    "capo": 0,
    "urlWeb": "https://tabs.ultimate-guitar.com/tab/juice-wrld/wishing-well-chords-3248528",
    "strumming": [],
    "videosCount": 19,
    "comments_count": 9,
    "contributor": {
        "user_id": 31132573,
        "username": "amh1mobile"
    },
    "advertising": {
        "targeting_song_genre": "hip hop"
    },
    "versions_count": 11,
    "pro_brother": {
        "id": 3508292,
        "song_id": 3983627,
        "song_name": "Wishing Well",
        "artist_id": 145437,
        "artist_name": "Juice WRLD",
        "type": "Official",
        "part": "",
        "version": 1,
        "votes": 26,
        "difficulty": "",
        "rating": 4.94497,
        "date": "1610467416",
        "status": "approved",
        "preset_id": 46514,
        "tab_access_type": "public",
        "tp_version": 0,
        "tonality_name": "C",
        "version_description": null,
        "verified": 0,
        "recording": {
            "is_acoustic": 0,
            "tonality_name": "",
            "performance": null,
            "recording_artists": [],
            "video_urls": null,
            "album_id": 576839
        },
        "album_cover": {
            "has_album_cover": true,
            "app_album_cover": {
                "small": "https://www.ultimate-guitar.com/static/s3/ugdb-p1/media/album/cover/1/6/1658843/primary-cover.jpg@200?c=1"
            }
        },
        "artist_cover": {
            "has_artist_cover": true,
            "app_artist_cover": {
                "small": "https://www.ultimate-guitar.com/static/s3/ugdb-p1/media/artist/cover/1/8/187365/primary-cover.jpg@200?c=1"
            }
        },
        "unique_chords": "",
        "ug_difficulty": "",
        "date_update": 1610467416,
        "source": ""
    },
    "recommended": [],
    "applicature": [
        {
            "chord": "C",
            "variations": [
                {
                    "id": "x32010",
                    "listCapos": [],
                    "noteIndex": 0,
                    "notes": [
                        52,
                        48,
                        43,
                        40,
                        36,
                        -1
                    ],
                    "frets": [
                        0,
                        1,
                        0,
                        2,
                        3,
                        -1
                    ],
                    "fingers": [
                        0,
                        1,
                        0,
                        2,
                        3,
                        0
                    ],
                    "fret": 0,
                    "type": "MAJOR",
                    "baseDisplayNote": ""
                },
                {
                    "id": "x32013",
                    "listCapos": [],
                    "noteIndex": 0,
                    "notes": [
                        55,
                        48,
                        43,
                        40,
                        36,
                        -1
                    ],
                    "frets": [
                        3,
                        1,
                        0,
                        2,
                        3,
                        -1
                    ],
                    "fingers": [
                        4,
                        1,
                        0,
                        2,
                        3,
                        0
                    ],
                    "fret": 0,
                    "type": "MAJOR",
                    "baseDisplayNote": ""
                },
                {
                    "id": "x35553",
                    "listCapos": [
                        {
                            "fret": 3,
                            "startString": 0,
                            "lastString": 4,
                            "finger": 1
                        }
                    ],
                    "noteIndex": 0,
                    "notes": [
                        55,
                        52,
                        48,
                        43,
                        36,
                        -1
                    ],
                    "frets": [
                        3,
                        5,
                        5,
                        5,
                        3,
                        -1
                    ],
                    "fingers": [
                        0,
                        4,
                        3,
                        2,
                        0,
                        0
                    ],
                    "fret": 3,
                    "type": "MAJOR",
                    "baseDisplayNote": ""
                },
                {
                    "id": "81010988",
                    "listCapos": [
                        {
                            "fret": 8,
                            "startString": 0,
                            "lastString": 5,
                            "finger": 1
                        }
                    ],
                    "noteIndex": 0,
                    "notes": [
                        60,
                        55,
                        52,
                        48,
                        43,
                        36
                    ],
                    "frets": [
                        8,
                        8,
                        9,
                        10,
                        10,
                        8
                    ],
                    "fingers": [
                        0,
                        0,
                        2,
                        4,
                        3,
                        0
                    ],
                    "fret": 8,
                    "type": "MAJOR",
                    "baseDisplayNote": ""
                },
                {
                    "id": "xx10988",
                    "listCapos": [
                        {
                            "fret": 8,
                            "startString": 0,
                            "lastString": 1,
                            "finger": 1
                        }
                    ],
                    "noteIndex": 0,
                    "notes": [
                        60,
                        55,
                        52,
                        48,
                        -1,
                        -1
                    ],
                    "frets": [
                        8,
                        8,
                        9,
                        10,
                        -1,
                        -1
                    ],
                    "fingers": [
                        0,
                        0,
                        2,
                        3,
                        0,
                        0
                    ],
                    "fret": 8,
                    "type": "MAJOR",
                    "baseDisplayNote": ""
                },
                {
                    "id": "xx10121312",
                    "listCapos": [],
                    "noteIndex": 0,
                    "notes": [
                        64,
                        60,
                        55,
                        48,
                        -1,
                        -1
                    ],
                    "frets": [
                        12,
                        13,
                        12,
                        10,
                        -1,
                        -1
                    ],
                    "fingers": [
                        3,
                        4,
                        2,
                        1,
                        0,
                        0
                    ],
                    "fret": 10,
                    "type": "MAJOR",
                    "baseDisplayNote": ""
                },
                {
                    "id": "x3201x",
                    "listCapos": [],
                    "noteIndex": 0,
                    "notes": [
                        -1,
                        48,
                        43,
                        40,
                        36,
                        -1
                    ],
                    "frets": [
                        -1,
                        1,
                        0,
                        2,
                        3,
                        -1
                    ],
                    "fingers": [
                        0,
                        1,
                        0,
                        2,
                        3,
                        0
                    ],
                    "fret": 0,
                    "type": "MAJOR",
                    "baseDisplayNote": ""
                },
                {
                    "id": "x3555x",
                    "listCapos": [
                        {
                            "fret": 5,
                            "startString": 1,
                            "lastString": 3,
                            "finger": 3
                        }
                    ],
                    "noteIndex": 0,
                    "notes": [
                        -1,
                        52,
                        48,
                        43,
                        36,
                        -1
                    ],
                    "frets": [
                        -1,
                        5,
                        5,
                        5,
                        3,
                        -1
                    ],
                    "fingers": [
                        0,
                        0,
                        0,
                        0,
                        1,
                        0
                    ],
                    "fret": 3,
                    "type": "MAJOR",
                    "baseDisplayNote": ""
                },
                {
                    "id": "87555x",
                    "listCapos": [
                        {
                            "fret": 5,
                            "startString": 1,
                            "lastString": 3,
                            "finger": 1
                        }
                    ],
                    "noteIndex": 0,
                    "notes": [
                        -1,
                        52,
                        48,
                        43,
                        40,
                        36
                    ],
                    "frets": [
                        -1,
                        5,
                        5,
                        5,
                        7,
                        8
                    ],
                    "fingers": [
                        0,
                        0,
                        0,
                        0,
                        3,
                        4
                    ],
                    "fret": 5,
                    "type": "MAJOR",
                    "baseDisplayNote": ""
                },
                {
                    "id": "8101098x",
                    "listCapos": [
                        {
                            "fret": 8,
                            "startString": 1,
                            "lastString": 5,
                            "finger": 1
                        }
                    ],
                    "noteIndex": 0,
                    "notes": [
                        -1,
                        55,
                        52,
                        48,
                        43,
                        36
                    ],
                    "frets": [
                        -1,
                        8,
                        9,
                        10,
                        10,
                        8
                    ],
                    "fingers": [
                        0,
                        0,
                        2,
                        4,
                        3,
                        0
                    ],
                    "fret": 8,
                    "type": "MAJOR",
                    "baseDisplayNote": ""
                },
                {
                    "id": "8755xx",
                    "listCapos": [
                        {
                            "fret": 5,
                            "startString": 2,
                            "lastString": 3,
                            "finger": 1
                        }
                    ],
                    "noteIndex": 0,
                    "notes": [
                        -1,
                        -1,
                        48,
                        43,
                        40,
                        36
                    ],
                    "frets": [
                        -1,
                        -1,
                        5,
                        5,
                        7,
                        8
                    ],
                    "fingers": [
                        0,
                        0,
                        0,
                        0,
                        3,
                        4
                    ],
                    "fret": 5,
                    "type": "MAJOR",
                    "baseDisplayNote": ""
                },
                {
                    "id": "810109xx",
                    "listCapos": [],
                    "noteIndex": 0,
                    "notes": [
                        -1,
                        -1,
                        52,
                        48,
                        43,
                        36
                    ],
                    "frets": [
                        -1,
                        -1,
                        9,
                        10,
                        10,
                        8
                    ],
                    "fingers": [
                        0,
                        0,
                        2,
                        4,
                        3,
                        1
                    ],
                    "fret": 8,
                    "type": "MAJOR",
                    "baseDisplayNote": ""
                },
                {
                    "id": "x3x010",
                    "listCapos": [],
                    "noteIndex": 0,
                    "notes": [
                        52,
                        48,
                        43,
                        -1,
                        36,
                        -1
                    ],
                    "frets": [
                        0,
                        1,
                        0,
                        -1,
                        3,
                        -1
                    ],
                    "fingers": [
                        0,
                        1,
                        0,
                        0,
                        3,
                        0
                    ],
                    "fret": 0,
                    "type": "MAJOR",
                    "baseDisplayNote": ""
                },
                {
                    "id": "x3x553",
                    "listCapos": [
                        {
                            "fret": 3,
                            "startString": 0,
                            "lastString": 4,
                            "finger": 1
                        }
                    ],
                    "noteIndex": 0,
                    "notes": [
                        55,
                        52,
                        48,
                        -1,
                        36,
                        -1
                    ],
                    "frets": [
                        3,
                        5,
                        5,
                        -1,
                        3,
                        -1
                    ],
                    "fingers": [
                        0,
                        4,
                        3,
                        0,
                        0,
                        0
                    ],
                    "fret": 3,
                    "type": "MAJOR",
                    "baseDisplayNote": ""
                },
                {
                    "id": "8x10988",
                    "listCapos": [
                        {
                            "fret": 8,
                            "startString": 0,
                            "lastString": 5,
                            "finger": 1
                        }
                    ],
                    "noteIndex": 0,
                    "notes": [
                        60,
                        55,
                        52,
                        48,
                        -1,
                        36
                    ],
                    "frets": [
                        8,
                        8,
                        9,
                        10,
                        -1,
                        8
                    ],
                    "fingers": [
                        0,
                        0,
                        2,
                        3,
                        0,
                        0
                    ],
                    "fret": 8,
                    "type": "MAJOR",
                    "baseDisplayNote": ""
                },
                {
                    "id": "8x555x",
                    "listCapos": [
                        {
                            "fret": 5,
                            "startString": 1,
                            "lastString": 3,
                            "finger": 1
                        }
                    ],
                    "noteIndex": 0,
                    "notes": [
                        -1,
                        52,
                        48,
                        43,
                        -1,
                        36
                    ],
                    "frets": [
                        -1,
                        5,
                        5,
                        5,
                        -1,
                        8
                    ],
                    "fingers": [
                        0,
                        0,
                        0,
                        0,
                        0,
                        4
                    ],
                    "fret": 5,
                    "type": "MAJOR",
                    "baseDisplayNote": ""
                },
                {
                    "id": "8x1098x",
                    "listCapos": [
                        {
                            "fret": 8,
                            "startString": 1,
                            "lastString": 5,
                            "finger": 1
                        }
                    ],
                    "noteIndex": 0,
                    "notes": [
                        -1,
                        55,
                        52,
                        48,
                        -1,
                        36
                    ],
                    "frets": [
                        -1,
                        8,
                        9,
                        10,
                        -1,
                        8
                    ],
                    "fingers": [
                        0,
                        0,
                        2,
                        3,
                        0,
                        0
                    ],
                    "fret": 8,
                    "type": "MAJOR",
                    "baseDisplayNote": ""
                }
            ]
        },
        {
            "chord": "Dm",
            "variations": [
                {
                    "id": "xx0231",
                    "listCapos": [],
                    "noteIndex": 2,
                    "notes": [
                        53,
                        50,
                        45,
                        38,
                        -1,
                        -1
                    ],
                    "frets": [
                        1,
                        3,
                        2,
                        0,
                        -1,
                        -1
                    ],
                    "fingers": [
                        1,
                        3,
                        2,
                        0,
                        0,
                        0
                    ],
                    "fret": 0,
                    "type": "MINOR",
                    "baseDisplayNote": ""
                },
                {
                    "id": "xx0765",
                    "listCapos": [],
                    "noteIndex": 2,
                    "notes": [
                        57,
                        53,
                        50,
                        38,
                        -1,
                        -1
                    ],
                    "frets": [
                        5,
                        6,
                        7,
                        0,
                        -1,
                        -1
                    ],
                    "fingers": [
                        1,
                        2,
                        3,
                        0,
                        0,
                        0
                    ],
                    "fret": 5,
                    "type": "MINOR",
                    "baseDisplayNote": ""
                },
                {
                    "id": "x57765",
                    "listCapos": [
                        {
                            "fret": 5,
                            "startString": 0,
                            "lastString": 4,
                            "finger": 1
                        }
                    ],
                    "noteIndex": 2,
                    "notes": [
                        57,
                        53,
                        50,
                        45,
                        38,
                        -1
                    ],
                    "frets": [
                        5,
                        6,
                        7,
                        7,
                        5,
                        -1
                    ],
                    "fingers": [
                        0,
                        2,
                        4,
                        3,
                        0,
                        0
                    ],
                    "fret": 5,
                    "type": "MINOR",
                    "baseDisplayNote": ""
                },
                {
                    "id": "xx0101010",
                    "listCapos": [
                        {
                            "fret": 10,
                            "startString": 0,
                            "lastString": 2,
                            "finger": 1
                        }
                    ],
                    "noteIndex": 2,
                    "notes": [
                        62,
                        57,
                        53,
                        38,
                        -1,
                        -1
                    ],
                    "frets": [
                        10,
                        10,
                        10,
                        0,
                        -1,
                        -1
                    ],
                    "fingers": [
                        0,
                        0,
                        0,
                        0,
                        0,
                        0
                    ],
                    "fret": 10,
                    "type": "MINOR",
                    "baseDisplayNote": ""
                },
                {
                    "id": "xx0101013",
                    "listCapos": [
                        {
                            "fret": 10,
                            "startString": 1,
                            "lastString": 2,
                            "finger": 1
                        }
                    ],
                    "noteIndex": 2,
                    "notes": [
                        65,
                        57,
                        53,
                        38,
                        -1,
                        -1
                    ],
                    "frets": [
                        13,
                        10,
                        10,
                        0,
                        -1,
                        -1
                    ],
                    "fingers": [
                        4,
                        0,
                        0,
                        0,
                        0,
                        0
                    ],
                    "fret": 10,
                    "type": "MINOR",
                    "baseDisplayNote": ""
                },
                {
                    "id": "101212101010",
                    "listCapos": [
                        {
                            "fret": 10,
                            "startString": 0,
                            "lastString": 5,
                            "finger": 1
                        }
                    ],
                    "noteIndex": 2,
                    "notes": [
                        62,
                        57,
                        53,
                        50,
                        45,
                        38
                    ],
                    "frets": [
                        10,
                        10,
                        10,
                        12,
                        12,
                        10
                    ],
                    "fingers": [
                        0,
                        0,
                        0,
                        4,
                        3,
                        0
                    ],
                    "fret": 10,
                    "type": "MINOR",
                    "baseDisplayNote": ""
                },
                {
                    "id": "101212101013",
                    "listCapos": [
                        {
                            "fret": 10,
                            "startString": 1,
                            "lastString": 5,
                            "finger": 1
                        }
                    ],
                    "noteIndex": 2,
                    "notes": [
                        65,
                        57,
                        53,
                        50,
                        45,
                        38
                    ],
                    "frets": [
                        13,
                        10,
                        10,
                        12,
                        12,
                        10
                    ],
                    "fingers": [
                        4,
                        0,
                        0,
                        3,
                        2,
                        0
                    ],
                    "fret": 10,
                    "type": "MINOR",
                    "baseDisplayNote": ""
                },
                {
                    "id": "xx12101010",
                    "listCapos": [
                        {
                            "fret": 10,
                            "startString": 0,
                            "lastString": 2,
                            "finger": 1
                        }
                    ],
                    "noteIndex": 2,
                    "notes": [
                        62,
                        57,
                        53,
                        50,
                        -1,
                        -1
                    ],
                    "frets": [
                        10,
                        10,
                        10,
                        12,
                        -1,
                        -1
                    ],
                    "fingers": [
                        0,
                        0,
                        0,
                        3,
                        0,
                        0
                    ],
                    "fret": 10,
                    "type": "MINOR",
                    "baseDisplayNote": ""
                },
                {
                    "id": "xx12101013",
                    "listCapos": [
                        {
                            "fret": 10,
                            "startString": 1,
                            "lastString": 2,
                            "finger": 1
                        }
                    ],
                    "noteIndex": 2,
                    "notes": [
                        65,
                        57,
                        53,
                        50,
                        -1,
                        -1
                    ],
                    "frets": [
                        13,
                        10,
                        10,
                        12,
                        -1,
                        -1
                    ],
                    "fingers": [
                        4,
                        0,
                        0,
                        3,
                        0,
                        0
                    ],
                    "fret": 10,
                    "type": "MINOR",
                    "baseDisplayNote": ""
                },
                {
                    "id": "x5776x",
                    "listCapos": [],
                    "noteIndex": 2,
                    "notes": [
                        -1,
                        53,
                        50,
                        45,
                        38,
                        -1
                    ],
                    "frets": [
                        -1,
                        6,
                        7,
                        7,
                        5,
                        -1
                    ],
                    "fingers": [
                        0,
                        2,
                        4,
                        3,
                        1,
                        0
                    ],
                    "fret": 5,
                    "type": "MINOR",
                    "baseDisplayNote": ""
                },
                {
                    "id": "1012121010x",
                    "listCapos": [
                        {
                            "fret": 10,
                            "startString": 1,
                            "lastString": 5,
                            "finger": 1
                        }
                    ],
                    "noteIndex": 2,
                    "notes": [
                        -1,
                        57,
                        53,
                        50,
                        45,
                        38
                    ],
                    "frets": [
                        -1,
                        10,
                        10,
                        12,
                        12,
                        10
                    ],
                    "fingers": [
                        0,
                        0,
                        0,
                        4,
                        3,
                        0
                    ],
                    "fret": 10,
                    "type": "MINOR",
                    "baseDisplayNote": ""
                },
                {
                    "id": "10877xx",
                    "listCapos": [
                        {
                            "fret": 7,
                            "startString": 2,
                            "lastString": 3,
                            "finger": 1
                        }
                    ],
                    "noteIndex": 2,
                    "notes": [
                        -1,
                        -1,
                        50,
                        45,
                        41,
                        38
                    ],
                    "frets": [
                        -1,
                        -1,
                        7,
                        7,
                        8,
                        10
                    ],
                    "fingers": [
                        0,
                        0,
                        0,
                        0,
                        2,
                        4
                    ],
                    "fret": 7,
                    "type": "MINOR",
                    "baseDisplayNote": ""
                },
                {
                    "id": "10121210xx",
                    "listCapos": [
                        {
                            "fret": 10,
                            "startString": 2,
                            "lastString": 5,
                            "finger": 1
                        }
                    ],
                    "noteIndex": 2,
                    "notes": [
                        -1,
                        -1,
                        53,
                        50,
                        45,
                        38
                    ],
                    "frets": [
                        -1,
                        -1,
                        10,
                        12,
                        12,
                        10
                    ],
                    "fingers": [
                        0,
                        0,
                        0,
                        4,
                        3,
                        0
                    ],
                    "fret": 10,
                    "type": "MINOR",
                    "baseDisplayNote": ""
                },
                {
                    "id": "x5x765",
                    "listCapos": [
                        {
                            "fret": 5,
                            "startString": 0,
                            "lastString": 4,
                            "finger": 1
                        }
                    ],
                    "noteIndex": 2,
                    "notes": [
                        57,
                        53,
                        50,
                        -1,
                        38,
                        -1
                    ],
                    "frets": [
                        5,
                        6,
                        7,
                        -1,
                        5,
                        -1
                    ],
                    "fingers": [
                        0,
                        2,
                        3,
                        0,
                        0,
                        0
                    ],
                    "fret": 5,
                    "type": "MINOR",
                    "baseDisplayNote": ""
                },
                {
                    "id": "10x12101010",
                    "listCapos": [
                        {
                            "fret": 10,
                            "startString": 0,
                            "lastString": 5,
                            "finger": 1
                        }
                    ],
                    "noteIndex": 2,
                    "notes": [
                        62,
                        57,
                        53,
                        50,
                        -1,
                        38
                    ],
                    "frets": [
                        10,
                        10,
                        10,
                        12,
                        -1,
                        10
                    ],
                    "fingers": [
                        0,
                        0,
                        0,
                        3,
                        0,
                        0
                    ],
                    "fret": 10,
                    "type": "MINOR",
                    "baseDisplayNote": ""
                },
                {
                    "id": "10x12101013",
                    "listCapos": [
                        {
                            "fret": 10,
                            "startString": 1,
                            "lastString": 5,
                            "finger": 1
                        }
                    ],
                    "noteIndex": 2,
                    "notes": [
                        65,
                        57,
                        53,
                        50,
                        -1,
                        38
                    ],
                    "frets": [
                        13,
                        10,
                        10,
                        12,
                        -1,
                        10
                    ],
                    "fingers": [
                        4,
                        0,
                        0,
                        3,
                        0,
                        0
                    ],
                    "fret": 10,
                    "type": "MINOR",
                    "baseDisplayNote": ""
                },
                {
                    "id": "10x121010x",
                    "listCapos": [
                        {
                            "fret": 10,
                            "startString": 1,
                            "lastString": 5,
                            "finger": 1
                        }
                    ],
                    "noteIndex": 2,
                    "notes": [
                        -1,
                        57,
                        53,
                        50,
                        -1,
                        38
                    ],
                    "frets": [
                        -1,
                        10,
                        10,
                        12,
                        -1,
                        10
                    ],
                    "fingers": [
                        0,
                        0,
                        0,
                        3,
                        0,
                        0
                    ],
                    "fret": 10,
                    "type": "MINOR",
                    "baseDisplayNote": ""
                }
            ]
        },
        {
            "chord": "Am",
            "variations": [
                {
                    "id": "x02210",
                    "listCapos": [],
                    "noteIndex": 9,
                    "notes": [
                        52,
                        48,
                        45,
                        40,
                        33,
                        -1
                    ],
                    "frets": [
                        0,
                        1,
                        2,
                        2,
                        0,
                        -1
                    ],
                    "fingers": [
                        0,
                        1,
                        3,
                        2,
                        0,
                        0
                    ],
                    "fret": 0,
                    "type": "MINOR",
                    "baseDisplayNote": ""
                },
                {
                    "id": "x02555",
                    "listCapos": [
                        {
                            "fret": 5,
                            "startString": 0,
                            "lastString": 2,
                            "finger": 4
                        }
                    ],
                    "noteIndex": 9,
                    "notes": [
                        57,
                        52,
                        48,
                        40,
                        33,
                        -1
                    ],
                    "frets": [
                        5,
                        5,
                        5,
                        2,
                        0,
                        -1
                    ],
                    "fingers": [
                        0,
                        0,
                        0,
                        1,
                        0,
                        0
                    ],
                    "fret": 0,
                    "type": "MINOR",
                    "baseDisplayNote": ""
                },
                {
                    "id": "x07555",
                    "listCapos": [
                        {
                            "fret": 5,
                            "startString": 0,
                            "lastString": 2,
                            "finger": 1
                        }
                    ],
                    "noteIndex": 9,
                    "notes": [
                        57,
                        52,
                        48,
                        45,
                        33,
                        -1
                    ],
                    "frets": [
                        5,
                        5,
                        5,
                        7,
                        0,
                        -1
                    ],
                    "fingers": [
                        0,
                        0,
                        0,
                        3,
                        0,
                        0
                    ],
                    "fret": 5,
                    "type": "MINOR",
                    "baseDisplayNote": ""
                },
                {
                    "id": "x07558",
                    "listCapos": [
                        {
                            "fret": 5,
                            "startString": 1,
                            "lastString": 2,
                            "finger": 1
                        }
                    ],
                    "noteIndex": 9,
                    "notes": [
                        60,
                        52,
                        48,
                        45,
                        33,
                        -1
                    ],
                    "frets": [
                        8,
                        5,
                        5,
                        7,
                        0,
                        -1
                    ],
                    "fingers": [
                        4,
                        0,
                        0,
                        3,
                        0,
                        0
                    ],
                    "fret": 5,
                    "type": "MINOR",
                    "baseDisplayNote": ""
                },
                {
                    "id": "577555",
                    "listCapos": [
                        {
                            "fret": 5,
                            "startString": 0,
                            "lastString": 5,
                            "finger": 1
                        }
                    ],
                    "noteIndex": 9,
                    "notes": [
                        57,
                        52,
                        48,
                        45,
                        40,
                        33
                    ],
                    "frets": [
                        5,
                        5,
                        5,
                        7,
                        7,
                        5
                    ],
                    "fingers": [
                        0,
                        0,
                        0,
                        4,
                        3,
                        0
                    ],
                    "fret": 5,
                    "type": "MINOR",
                    "baseDisplayNote": ""
                },
                {
                    "id": "577558",
                    "listCapos": [
                        {
                            "fret": 5,
                            "startString": 1,
                            "lastString": 5,
                            "finger": 1
                        }
                    ],
                    "noteIndex": 9,
                    "notes": [
                        60,
                        52,
                        48,
                        45,
                        40,
                        33
                    ],
                    "frets": [
                        8,
                        5,
                        5,
                        7,
                        7,
                        5
                    ],
                    "fingers": [
                        4,
                        0,
                        0,
                        3,
                        2,
                        0
                    ],
                    "fret": 5,
                    "type": "MINOR",
                    "baseDisplayNote": ""
                },
                {
                    "id": "xx7555",
                    "listCapos": [
                        {
                            "fret": 5,
                            "startString": 0,
                            "lastString": 2,
                            "finger": 1
                        }
                    ],
                    "noteIndex": 9,
                    "notes": [
                        57,
                        52,
                        48,
                        45,
                        -1,
                        -1
                    ],
                    "frets": [
                        5,
                        5,
                        5,
                        7,
                        -1,
                        -1
                    ],
                    "fingers": [
                        0,
                        0,
                        0,
                        3,
                        0,
                        0
                    ],
                    "fret": 5,
                    "type": "MINOR",
                    "baseDisplayNote": ""
                },
                {
                    "id": "xx7558",
                    "listCapos": [
                        {
                            "fret": 5,
                            "startString": 1,
                            "lastString": 2,
                            "finger": 1
                        }
                    ],
                    "noteIndex": 9,
                    "notes": [
                        60,
                        52,
                        48,
                        45,
                        -1,
                        -1
                    ],
                    "frets": [
                        8,
                        5,
                        5,
                        7,
                        -1,
                        -1
                    ],
                    "fingers": [
                        4,
                        0,
                        0,
                        3,
                        0,
                        0
                    ],
                    "fret": 5,
                    "type": "MINOR",
                    "baseDisplayNote": ""
                },
                {
                    "id": "x079108",
                    "listCapos": [],
                    "noteIndex": 9,
                    "notes": [
                        60,
                        57,
                        52,
                        45,
                        33,
                        -1
                    ],
                    "frets": [
                        8,
                        10,
                        9,
                        7,
                        0,
                        -1
                    ],
                    "fingers": [
                        2,
                        4,
                        3,
                        1,
                        0,
                        0
                    ],
                    "fret": 7,
                    "type": "MINOR",
                    "baseDisplayNote": ""
                },
                {
                    "id": "xx79108",
                    "listCapos": [],
                    "noteIndex": 9,
                    "notes": [
                        60,
                        57,
                        52,
                        45,
                        -1,
                        -1
                    ],
                    "frets": [
                        8,
                        10,
                        9,
                        7,
                        -1,
                        -1
                    ],
                    "fingers": [
                        2,
                        4,
                        3,
                        1,
                        0,
                        0
                    ],
                    "fret": 7,
                    "type": "MINOR",
                    "baseDisplayNote": ""
                },
                {
                    "id": "x0109108",
                    "listCapos": [],
                    "noteIndex": 9,
                    "notes": [
                        60,
                        57,
                        52,
                        48,
                        33,
                        -1
                    ],
                    "frets": [
                        8,
                        10,
                        9,
                        10,
                        0,
                        -1
                    ],
                    "fingers": [
                        1,
                        4,
                        2,
                        3,
                        0,
                        0
                    ],
                    "fret": 8,
                    "type": "MINOR",
                    "baseDisplayNote": ""
                },
                {
                    "id": "x0255x",
                    "listCapos": [
                        {
                            "fret": 5,
                            "startString": 1,
                            "lastString": 2,
                            "finger": 4
                        }
                    ],
                    "noteIndex": 9,
                    "notes": [
                        -1,
                        52,
                        48,
                        40,
                        33,
                        -1
                    ],
                    "frets": [
                        -1,
                        5,
                        5,
                        2,
                        0,
                        -1
                    ],
                    "fingers": [
                        0,
                        0,
                        0,
                        1,
                        0,
                        0
                    ],
                    "fret": 0,
                    "type": "MINOR",
                    "baseDisplayNote": ""
                },
                {
                    "id": "x0221x",
                    "listCapos": [],
                    "noteIndex": 9,
                    "notes": [
                        -1,
                        48,
                        45,
                        40,
                        33,
                        -1
                    ],
                    "frets": [
                        -1,
                        1,
                        2,
                        2,
                        0,
                        -1
                    ],
                    "fingers": [
                        0,
                        1,
                        3,
                        2,
                        0,
                        0
                    ],
                    "fret": 0,
                    "type": "MINOR",
                    "baseDisplayNote": ""
                },
                {
                    "id": "x0755x",
                    "listCapos": [
                        {
                            "fret": 5,
                            "startString": 1,
                            "lastString": 2,
                            "finger": 1
                        }
                    ],
                    "noteIndex": 9,
                    "notes": [
                        -1,
                        52,
                        48,
                        45,
                        33,
                        -1
                    ],
                    "frets": [
                        -1,
                        5,
                        5,
                        7,
                        0,
                        -1
                    ],
                    "fingers": [
                        0,
                        0,
                        0,
                        3,
                        0,
                        0
                    ],
                    "fret": 5,
                    "type": "MINOR",
                    "baseDisplayNote": ""
                },
                {
                    "id": "57755x",
                    "listCapos": [
                        {
                            "fret": 5,
                            "startString": 1,
                            "lastString": 5,
                            "finger": 1
                        }
                    ],
                    "noteIndex": 9,
                    "notes": [
                        -1,
                        52,
                        48,
                        45,
                        40,
                        33
                    ],
                    "frets": [
                        -1,
                        5,
                        5,
                        7,
                        7,
                        5
                    ],
                    "fingers": [
                        0,
                        0,
                        0,
                        4,
                        3,
                        0
                    ],
                    "fret": 5,
                    "type": "MINOR",
                    "baseDisplayNote": ""
                },
                {
                    "id": "x010910x",
                    "listCapos": [],
                    "noteIndex": 9,
                    "notes": [
                        -1,
                        57,
                        52,
                        48,
                        33,
                        -1
                    ],
                    "frets": [
                        -1,
                        10,
                        9,
                        10,
                        0,
                        -1
                    ],
                    "fingers": [
                        0,
                        3,
                        1,
                        2,
                        0,
                        0
                    ],
                    "fret": 9,
                    "type": "MINOR",
                    "baseDisplayNote": ""
                },
                {
                    "id": "5322xx",
                    "listCapos": [
                        {
                            "fret": 2,
                            "startString": 2,
                            "lastString": 3,
                            "finger": 1
                        }
                    ],
                    "noteIndex": 9,
                    "notes": [
                        -1,
                        -1,
                        45,
                        40,
                        36,
                        33
                    ],
                    "frets": [
                        -1,
                        -1,
                        2,
                        2,
                        3,
                        5
                    ],
                    "fingers": [
                        0,
                        0,
                        0,
                        0,
                        2,
                        4
                    ],
                    "fret": 2,
                    "type": "MINOR",
                    "baseDisplayNote": ""
                },
                {
                    "id": "5775xx",
                    "listCapos": [
                        {
                            "fret": 5,
                            "startString": 2,
                            "lastString": 5,
                            "finger": 1
                        }
                    ],
                    "noteIndex": 9,
                    "notes": [
                        -1,
                        -1,
                        48,
                        45,
                        40,
                        33
                    ],
                    "frets": [
                        -1,
                        -1,
                        5,
                        7,
                        7,
                        5
                    ],
                    "fingers": [
                        0,
                        0,
                        0,
                        4,
                        3,
                        0
                    ],
                    "fret": 5,
                    "type": "MINOR",
                    "baseDisplayNote": ""
                },
                {
                    "id": "x0x210",
                    "listCapos": [],
                    "noteIndex": 9,
                    "notes": [
                        52,
                        48,
                        45,
                        -1,
                        33,
                        -1
                    ],
                    "frets": [
                        0,
                        1,
                        2,
                        -1,
                        0,
                        -1
                    ],
                    "fingers": [
                        0,
                        1,
                        2,
                        0,
                        0,
                        0
                    ],
                    "fret": 0,
                    "type": "MINOR",
                    "baseDisplayNote": ""
                },
                {
                    "id": "5x7555",
                    "listCapos": [
                        {
                            "fret": 5,
                            "startString": 0,
                            "lastString": 5,
                            "finger": 1
                        }
                    ],
                    "noteIndex": 9,
                    "notes": [
                        57,
                        52,
                        48,
                        45,
                        -1,
                        33
                    ],
                    "frets": [
                        5,
                        5,
                        5,
                        7,
                        -1,
                        5
                    ],
                    "fingers": [
                        0,
                        0,
                        0,
                        3,
                        0,
                        0
                    ],
                    "fret": 5,
                    "type": "MINOR",
                    "baseDisplayNote": ""
                },
                {
                    "id": "5x7558",
                    "listCapos": [
                        {
                            "fret": 5,
                            "startString": 1,
                            "lastString": 5,
                            "finger": 1
                        }
                    ],
                    "noteIndex": 9,
                    "notes": [
                        60,
                        52,
                        48,
                        45,
                        -1,
                        33
                    ],
                    "frets": [
                        8,
                        5,
                        5,
                        7,
                        -1,
                        5
                    ],
                    "fingers": [
                        4,
                        0,
                        0,
                        3,
                        0,
                        0
                    ],
                    "fret": 5,
                    "type": "MINOR",
                    "baseDisplayNote": ""
                },
                {
                    "id": "5x755x",
                    "listCapos": [
                        {
                            "fret": 5,
                            "startString": 1,
                            "lastString": 5,
                            "finger": 1
                        }
                    ],
                    "noteIndex": 9,
                    "notes": [
                        -1,
                        52,
                        48,
                        45,
                        -1,
                        33
                    ],
                    "frets": [
                        -1,
                        5,
                        5,
                        7,
                        -1,
                        5
                    ],
                    "fingers": [
                        0,
                        0,
                        0,
                        3,
                        0,
                        0
                    ],
                    "fret": 5,
                    "type": "MINOR",
                    "baseDisplayNote": ""
                }
            ]
        },
        {
            "chord": "F",
            "variations": [
                {
                    "id": "133211",
                    "listCapos": [
                        {
                            "fret": 1,
                            "startString": 0,
                            "lastString": 5,
                            "finger": 1
                        }
                    ],
                    "noteIndex": 5,
                    "notes": [
                        53,
                        48,
                        45,
                        41,
                        36,
                        29
                    ],
                    "frets": [
                        1,
                        1,
                        2,
                        3,
                        3,
                        1
                    ],
                    "fingers": [
                        0,
                        0,
                        2,
                        4,
                        3,
                        0
                    ],
                    "fret": 0,
                    "type": "MAJOR",
                    "baseDisplayNote": ""
                },
                {
                    "id": "xx3211",
                    "listCapos": [
                        {
                            "fret": 1,
                            "startString": 0,
                            "lastString": 1,
                            "finger": 1
                        }
                    ],
                    "noteIndex": 5,
                    "notes": [
                        53,
                        48,
                        45,
                        41,
                        -1,
                        -1
                    ],
                    "frets": [
                        1,
                        1,
                        2,
                        3,
                        -1,
                        -1
                    ],
                    "fingers": [
                        0,
                        0,
                        2,
                        3,
                        0,
                        0
                    ],
                    "fret": 0,
                    "type": "MAJOR",
                    "baseDisplayNote": ""
                },
                {
                    "id": "xx3565",
                    "listCapos": [],
                    "noteIndex": 5,
                    "notes": [
                        57,
                        53,
                        48,
                        41,
                        -1,
                        -1
                    ],
                    "frets": [
                        5,
                        6,
                        5,
                        3,
                        -1,
                        -1
                    ],
                    "fingers": [
                        3,
                        4,
                        2,
                        1,
                        0,
                        0
                    ],
                    "fret": 3,
                    "type": "MAJOR",
                    "baseDisplayNote": ""
                },
                {
                    "id": "x87565",
                    "listCapos": [
                        {
                            "fret": 5,
                            "startString": 0,
                            "lastString": 2,
                            "finger": 1
                        }
                    ],
                    "noteIndex": 5,
                    "notes": [
                        57,
                        53,
                        48,
                        45,
                        41,
                        -1
                    ],
                    "frets": [
                        5,
                        6,
                        5,
                        7,
                        8,
                        -1
                    ],
                    "fingers": [
                        0,
                        2,
                        0,
                        3,
                        4,
                        0
                    ],
                    "fret": 5,
                    "type": "MAJOR",
                    "baseDisplayNote": ""
                },
                {
                    "id": "x81010108",
                    "listCapos": [
                        {
                            "fret": 8,
                            "startString": 0,
                            "lastString": 4,
                            "finger": 1
                        }
                    ],
                    "noteIndex": 5,
                    "notes": [
                        60,
                        57,
                        53,
                        48,
                        41,
                        -1
                    ],
                    "frets": [
                        8,
                        10,
                        10,
                        10,
                        8,
                        -1
                    ],
                    "fingers": [
                        0,
                        4,
                        3,
                        2,
                        0,
                        0
                    ],
                    "fret": 8,
                    "type": "MAJOR",
                    "baseDisplayNote": ""
                },
                {
                    "id": "13321x",
                    "listCapos": [
                        {
                            "fret": 1,
                            "startString": 1,
                            "lastString": 5,
                            "finger": 1
                        }
                    ],
                    "noteIndex": 5,
                    "notes": [
                        -1,
                        48,
                        45,
                        41,
                        36,
                        29
                    ],
                    "frets": [
                        -1,
                        1,
                        2,
                        3,
                        3,
                        1
                    ],
                    "fingers": [
                        0,
                        0,
                        2,
                        4,
                        3,
                        0
                    ],
                    "fret": 0,
                    "type": "MAJOR",
                    "baseDisplayNote": ""
                },
                {
                    "id": "x8756x",
                    "listCapos": [],
                    "noteIndex": 5,
                    "notes": [
                        -1,
                        53,
                        48,
                        45,
                        41,
                        -1
                    ],
                    "frets": [
                        -1,
                        6,
                        5,
                        7,
                        8,
                        -1
                    ],
                    "fingers": [
                        0,
                        2,
                        1,
                        3,
                        4,
                        0
                    ],
                    "fret": 5,
                    "type": "MAJOR",
                    "baseDisplayNote": ""
                },
                {
                    "id": "x8101010x",
                    "listCapos": [
                        {
                            "fret": 10,
                            "startString": 1,
                            "lastString": 3,
                            "finger": 3
                        }
                    ],
                    "noteIndex": 5,
                    "notes": [
                        -1,
                        57,
                        53,
                        48,
                        41,
                        -1
                    ],
                    "frets": [
                        -1,
                        10,
                        10,
                        10,
                        8,
                        -1
                    ],
                    "fingers": [
                        0,
                        0,
                        0,
                        0,
                        1,
                        0
                    ],
                    "fret": 8,
                    "type": "MAJOR",
                    "baseDisplayNote": ""
                },
                {
                    "id": "1312101010x",
                    "listCapos": [
                        {
                            "fret": 10,
                            "startString": 1,
                            "lastString": 3,
                            "finger": 1
                        }
                    ],
                    "noteIndex": 5,
                    "notes": [
                        -1,
                        57,
                        53,
                        48,
                        45,
                        41
                    ],
                    "frets": [
                        -1,
                        10,
                        10,
                        10,
                        12,
                        13
                    ],
                    "fingers": [
                        0,
                        0,
                        0,
                        0,
                        3,
                        4
                    ],
                    "fret": 10,
                    "type": "MAJOR",
                    "baseDisplayNote": ""
                },
                {
                    "id": "1332xx",
                    "listCapos": [],
                    "noteIndex": 5,
                    "notes": [
                        -1,
                        -1,
                        45,
                        41,
                        36,
                        29
                    ],
                    "frets": [
                        -1,
                        -1,
                        2,
                        3,
                        3,
                        1
                    ],
                    "fingers": [
                        0,
                        0,
                        2,
                        4,
                        3,
                        1
                    ],
                    "fret": 0,
                    "type": "MAJOR",
                    "baseDisplayNote": ""
                },
                {
                    "id": "13121010xx",
                    "listCapos": [
                        {
                            "fret": 10,
                            "startString": 2,
                            "lastString": 3,
                            "finger": 1
                        }
                    ],
                    "noteIndex": 5,
                    "notes": [
                        -1,
                        -1,
                        53,
                        48,
                        45,
                        41
                    ],
                    "frets": [
                        -1,
                        -1,
                        10,
                        10,
                        12,
                        13
                    ],
                    "fingers": [
                        0,
                        0,
                        0,
                        0,
                        3,
                        4
                    ],
                    "fret": 10,
                    "type": "MAJOR",
                    "baseDisplayNote": ""
                },
                {
                    "id": "1x3211",
                    "listCapos": [
                        {
                            "fret": 1,
                            "startString": 0,
                            "lastString": 5,
                            "finger": 1
                        }
                    ],
                    "noteIndex": 5,
                    "notes": [
                        53,
                        48,
                        45,
                        41,
                        -1,
                        29
                    ],
                    "frets": [
                        1,
                        1,
                        2,
                        3,
                        -1,
                        1
                    ],
                    "fingers": [
                        0,
                        0,
                        2,
                        3,
                        0,
                        0
                    ],
                    "fret": 0,
                    "type": "MAJOR",
                    "baseDisplayNote": ""
                },
                {
                    "id": "x8x565",
                    "listCapos": [
                        {
                            "fret": 5,
                            "startString": 0,
                            "lastString": 2,
                            "finger": 1
                        }
                    ],
                    "noteIndex": 5,
                    "notes": [
                        57,
                        53,
                        48,
                        -1,
                        41,
                        -1
                    ],
                    "frets": [
                        5,
                        6,
                        5,
                        -1,
                        8,
                        -1
                    ],
                    "fingers": [
                        0,
                        2,
                        0,
                        0,
                        4,
                        0
                    ],
                    "fret": 5,
                    "type": "MAJOR",
                    "baseDisplayNote": ""
                },
                {
                    "id": "x8x10108",
                    "listCapos": [
                        {
                            "fret": 8,
                            "startString": 0,
                            "lastString": 4,
                            "finger": 1
                        }
                    ],
                    "noteIndex": 5,
                    "notes": [
                        60,
                        57,
                        53,
                        -1,
                        41,
                        -1
                    ],
                    "frets": [
                        8,
                        10,
                        10,
                        -1,
                        8,
                        -1
                    ],
                    "fingers": [
                        0,
                        4,
                        3,
                        0,
                        0,
                        0
                    ],
                    "fret": 8,
                    "type": "MAJOR",
                    "baseDisplayNote": ""
                },
                {
                    "id": "1x321x",
                    "listCapos": [
                        {
                            "fret": 1,
                            "startString": 1,
                            "lastString": 5,
                            "finger": 1
                        }
                    ],
                    "noteIndex": 5,
                    "notes": [
                        -1,
                        48,
                        45,
                        41,
                        -1,
                        29
                    ],
                    "frets": [
                        -1,
                        1,
                        2,
                        3,
                        -1,
                        1
                    ],
                    "fingers": [
                        0,
                        0,
                        2,
                        3,
                        0,
                        0
                    ],
                    "fret": 0,
                    "type": "MAJOR",
                    "baseDisplayNote": ""
                },
                {
                    "id": "13x101010x",
                    "listCapos": [
                        {
                            "fret": 10,
                            "startString": 1,
                            "lastString": 3,
                            "finger": 1
                        }
                    ],
                    "noteIndex": 5,
                    "notes": [
                        -1,
                        57,
                        53,
                        48,
                        -1,
                        41
                    ],
                    "frets": [
                        -1,
                        10,
                        10,
                        10,
                        -1,
                        13
                    ],
                    "fingers": [
                        0,
                        0,
                        0,
                        0,
                        0,
                        4
                    ],
                    "fret": 10,
                    "type": "MAJOR",
                    "baseDisplayNote": ""
                }
            ]
        }
    ],
    "content": "[Intro]\r\n\r\n[ch]C[/ch] [ch]Dm[/ch] [ch]Am[/ch] [ch]F[/ch] [ch]C[/ch]\r\n\r\n\r\n[tab][ch]Am[/ch]                        [ch]F[/ch]  [ch]C[/ch]\r\nWaiting for the exhale[/tab]\r\n[tab]          [ch]Am[/ch]                                     [ch]F[/ch]  [ch]C[/ch]\r\nI toss my pain with my wishes in a wishing well[/tab]\r\n\r\n\r\n[Chorus]\r\n[tab]        [ch]C[/ch]        [ch]Dm[/ch]                  [ch]Am[/ch]\r\nI can't breathe, I'm waiting for the exhale[/tab]\r\n[tab]        [ch]F[/ch]                   [ch]C[/ch]\r\nToss my pain with my wishes in a wishing well[/tab]\r\n[tab]         [ch]C[/ch]  [ch]Dm[/ch]     [ch]Am[/ch]\r\nStill no luck, but oh well[/tab]\r\n[tab]        [ch]F[/ch]                          [ch]C[/ch]\r\nI still try even though I know I'm gon' fail[/tab]\r\n[tab][ch]Am[/ch]\r\nStress on my shoulders like a anvil[/tab]\r\n[tab][ch]F[/ch]                           [ch]C[/ch]\r\nPerky got me itching like a anthill[/tab]\r\n[tab]      [ch]Am[/ch]\r\nDrugs killing me softly, Lauryn Hill[/tab]\r\n[tab]    [ch]F[/ch]                  [ch]C[/ch]\r\nSometimes I don't know how to feel[/tab]\r\n\r\n\r\n[Verse 1]\r\n[tab]     [ch]C[/ch]     [ch]Dm[/ch]              [ch]Am[/ch]\r\nRing-ring, phone call from depression[/tab]\r\n[tab]            [ch]F[/ch]                         [ch]C[/ch]\r\nYou used my past and my memories as a weapon[/tab]\r\n[tab]       [ch]C[/ch]           [ch]Dm[/ch]        [ch]Am[/ch]\r\nOn the other line, I talk to addiction, huh[/tab]\r\n[tab][ch]F[/ch]                              [ch]C[/ch]\r\nSpeaking of the devil, all the drugs, I miss them[/tab]\r\n[tab][ch]Am[/ch]\r\nThis can't be real, is it fiction?[/tab]\r\n[tab][ch]F[/ch]                              [ch]C[/ch]\r\nSomethin' feels broke, need to fix it[/tab]\r\n[tab][ch]Am[/ch]\r\nI cry out for help, do they listen?[/tab]\r\n[tab][ch]F[/ch]                        [ch]C[/ch]\r\nI'ma be alone until it's finished[/tab]\r\n\r\n\r\n[Pre-Chorus]\r\n[tab][ch]Am[/ch]                                                  [ch]F[/ch]\r\nThis is the part where I tell you I'm fine, but I'm lying[/tab]\r\n[tab]             [ch]C[/ch]\r\nI just don't want you to worry[/tab]\r\n[tab][ch]Am[/ch]                                                [ch]F[/ch]\r\nThis is the part where I take all my feelings and hide 'em[/tab]\r\n[tab]                      [ch]C[/ch]\r\n'Cause I don't want nobody to hurt me[/tab]\r\n\r\n\r\n[Chorus]\r\n[tab]        [ch]C[/ch]        [ch]Dm[/ch]                  [ch]Am[/ch]\r\nI can't breathe, I'm waiting for the exhale[/tab]\r\n[tab]        [ch]F[/ch]                   [ch]C[/ch]\r\nToss my pain with my wishes in a wishing well[/tab]\r\n[tab]         [ch]C[/ch]  [ch]Dm[/ch]     [ch]Am[/ch]\r\nStill no luck, but oh well[/tab]\r\n[tab]        [ch]F[/ch]                          [ch]C[/ch]\r\nI still try even though I know I'm gon' fail[/tab]\r\n[tab][ch]Am[/ch]\r\nStress on my shoulders like a anvil[/tab]\r\n[tab][ch]F[/ch]                           [ch]C[/ch]\r\nPerky got me itching like a anthill[/tab]\r\n[tab]      [ch]Am[/ch]\r\nDrugs killing me softly, Lauryn Hill[/tab]\r\n[tab]    [ch]F[/ch]                  [ch]C[/ch]\r\nSometimes I don't know how to feel[/tab]\r\n\r\n\r\n\r\n[Verse 2]\r\n[tab]    [ch]C[/ch]     [ch]Dm[/ch]           [ch]Am[/ch]\r\nSometimes I don't know how to feel[/tab]\r\n[tab]      [ch]F[/ch]\r\nLet's be for real[/tab]\r\n[tab]      [ch]C[/ch]                              [ch]C[/ch]       [ch]Dm[/ch]\r\nIf it wasn't for the pills, I wouldn't be here[/tab]\r\n[tab]              [ch]Am[/ch]                          [ch]F[/ch]        [ch]C[/ch]\r\nBut if I keep taking these pills, I won't be here, yeah[/tab]\r\n[tab]                     [ch]Am[/ch]\r\nI just told y'all my secret, yeah[/tab]\r\n[tab]                   [ch]F[/ch]   [ch]C[/ch]\r\nIt's tearing me to pieces[/tab]\r\n[tab]                 [ch]Am[/ch]\r\nI really think I need them[/tab]\r\n[tab]  [ch]F[/ch]                            [ch]C[/ch]\r\nI stopped taking the drugs and now the drugs take me[/tab]\r\n\r\n\r\n[Pre-Chorus]\r\n[tab][ch]Am[/ch]                                                  [ch]F[/ch]\r\nThis is the part where I tell you I'm fine, but I'm lying[/tab]\r\n[tab]             [ch]C[/ch]\r\nI just don't want you to worry[/tab]\r\n[tab][ch]Am[/ch]                                                [ch]F[/ch]\r\nThis is the part where I take all my feelings and hide 'em[/tab]\r\n[tab]                      [ch]C[/ch]\r\n'Cause I don't want nobody to hurt me[/tab]\r\n\r\n\r\n[Chorus]\r\n[tab]        [ch]C[/ch]        [ch]Dm[/ch]                  [ch]Am[/ch]\r\nI can't breathe, I'm waiting for the exhale[/tab]\r\n[tab]        [ch]F[/ch]                   [ch]C[/ch]\r\nToss my pain with my wishes in a wishing well[/tab]\r\n[tab]         [ch]C[/ch]  [ch]Dm[/ch]     [ch]Am[/ch]\r\nStill no luck, but oh well[/tab]\r\n[tab]        [ch]F[/ch]                          [ch]C[/ch]\r\nI still try even though I know I'm gon' fail[/tab]\r\n[tab][ch]Am[/ch]\r\nStress on my shoulders like a anvil[/tab]\r\n[tab][ch]F[/ch]                           [ch]C[/ch]\r\nPerky got me itching like a anthill[/tab]\r\n[tab]      [ch]Am[/ch]\r\nDrugs killing me softly, Lauryn Hill[/tab]\r\n[tab]    [ch]F[/ch]                  [ch]C[/ch]\r\nSometimes I don't know how to feel[/tab]",
    "is_backing_track_under_review": false,
    "is_tab_ml": false,
    "chart_year": 2020
}